ipm/__init__.py
ipm/cli.py
ipm/downloader.py
ipm/installer.py
ipm/progress.py
ipm_python-1.2.9.dist-info/LICENSE
ipm_python-1.2.9.dist-info/METADATA
ipm_python-1.2.9.dist-info/WHEEL
ipm_python-1.2.9.dist-info/entry_points.txt
ipm_python-1.2.9.dist-info/top_level.txt
ipm_python-1.2.9.dist-info/RECORD
