Metadata-Version: 2.1
Name: ipm-python
Version: 1.2.9
Summary: 改进版 Python 软件包管理器，支持国内镜像和动态进度条。
Home-page: https://github.com/IngotStudio/ipm
Author: IngotStudio
Author-email: xmz20130612@163.com
License: UNKNOWN
Platform: UNKNOWN
Classifier: Programming Language :: Python :: 3
Classifier: License :: OSI Approved :: MIT License
Classifier: Operating System :: OS Independent
Requires-Python: >=3.6
Requires-Dist: tqdm
